docker_dbdump/__init__.py
docker_dbdump/backup.py
docker_dbdump-0.3.0.dist-info/LICENSE
docker_dbdump-0.3.0.dist-info/METADATA
docker_dbdump-0.3.0.dist-info/WHEEL
docker_dbdump-0.3.0.dist-info/entry_points.txt
docker_dbdump-0.3.0.dist-info/RECORD
