Metadata-Version: 2.3
Name: docker-dbdump
Version: 0.3.0
Summary: 
Author: kmille
Author-email: github@androidloves.me
Requires-Python: >=3.11,<4.0
Classifier: Programming Language :: Python :: 3
Classifier: Programming Language :: Python :: 3.11
Classifier: Programming Language :: Python :: 3.12
Classifier: Programming Language :: Python :: 3.13
Requires-Dist: docker (>=7.0.0,<8.0.0)
